{
    "pf_chan3.mp3": [
        {
            "common_name": "Eurasian Jackdaw",
            "scientific_name": "Corvus monedula",
            "start_time": 951.0,
            "end_time": 954.0,
            "confidence": 0.5193613767623901
        }
    ],
    "sep_chan1.mp3": [
        {
            "common_name": "Eurasian Jackdaw",
            "scientific_name": "Corvus monedula",
            "start_time": 63.0,
            "end_time": 66.0,
            "confidence": 0.46055662631988525
        },
        {
            "common_name": "Ring-necked Pheasant",
            "scientific_name": "Phasianus colchicus",
            "start_time": 99.0,
            "end_time": 102.0,
            "confidence": 0.5425426363945007
        },
        {
            "common_name": "Eurasian Jackdaw",
            "scientific_name": "Corvus monedula",
            "start_time": 135.0,
            "end_time": 138.0,
            "confidence": 0.7086937427520752
        },
        {
            "common_name": "Eurasian Jackdaw",
            "scientific_name": "Corvus monedula",
            "start_time": 162.0,
            "end_time": 165.0,
            "confidence": 0.5243072509765625
        },
        {
            "common_name": "Eurasian Jackdaw",
            "scientific_name": "Corvus monedula",
            "start_time": 168.0,
            "end_time": 171.0,
            "confidence": 0.8085947632789612
        },
        {
            "common_name": "Eurasian Jackdaw",
            "scientific_name": "Corvus monedula",
            "start_time": 174.0,
            "end_time": 177.0,
            "confidence": 0.5455498695373535
        },
        {
            "common_name": "Eurasian Jackdaw",
            "scientific_name": "Corvus monedula",
            "start_time": 240.0,
            "end_time": 243.0,
            "confidence": 0.6729198694229126
        },
        {
            "common_name": "Eurasian Green Woodpecker",
            "scientific_name": "Picus viridis",
            "start_time": 261.0,
            "end_time": 264.0,
            "confidence": 0.9297938942909241
        },
        {
            "common_name": "Eurasian Jackdaw",
            "scientific_name": "Corvus monedula",
            "start_time": 312.0,
            "end_time": 315.0,
            "confidence": 0.5170925259590149
        },
        {
            "common_name": "Eurasian Jackdaw",
            "scientific_name": "Corvus monedula",
            "start_time": 315.0,
            "end_time": 318.0,
            "confidence": 0.8045922517776489
        },
        {
            "common_name": "Eurasian Jackdaw",
            "scientific_name": "Corvus monedula",
            "start_time": 339.0,
            "end_time": 342.0,
            "confidence": 0.8602504134178162
        },
        {
            "common_name": "Ring-necked Pheasant",
            "scientific_name": "Phasianus colchicus",
            "start_time": 411.0,
            "end_time": 414.0,
            "confidence": 0.7811874747276306
        },
        {
            "common_name": "Eurasian Jackdaw",
            "scientific_name": "Corvus monedula",
            "start_time": 441.0,
            "end_time": 444.0,
            "confidence": 0.48992371559143066
        },
        {
            "common_name": "Ring-necked Pheasant",
            "scientific_name": "Phasianus colchicus",
            "start_time": 642.0,
            "end_time": 645.0,
            "confidence": 0.7563855051994324
        },
        {
            "common_name": "Eurasian Jackdaw",
            "scientific_name": "Corvus monedula",
            "start_time": 753.0,
            "end_time": 756.0,
            "confidence": 0.44203412532806396
        },
        {
            "common_name": "Eurasian Jackdaw",
            "scientific_name": "Corvus monedula",
            "start_time": 945.0,
            "end_time": 948.0,
            "confidence": 0.6594182252883911
        },
        {
            "common_name": "Eurasian Jackdaw",
            "scientific_name": "Corvus monedula",
            "start_time": 951.0,
            "end_time": 954.0,
            "confidence": 0.5626723766326904
        },
        {
            "common_name": "Eurasian Jackdaw",
            "scientific_name": "Corvus monedula",
            "start_time": 1113.0,
            "end_time": 1116.0,
            "confidence": 0.8337604999542236
        },
        {
            "common_name": "Eurasian Jackdaw",
            "scientific_name": "Corvus monedula",
            "start_time": 1125.0,
            "end_time": 1128.0,
            "confidence": 0.7845629453659058
        }
    ],
    "sep_chan2.mp3": [
        {
            "common_name": "Eurasian Jackdaw",
            "scientific_name": "Corvus monedula",
            "start_time": 63.0,
            "end_time": 66.0,
            "confidence": 0.46820083260536194
        },
        {
            "common_name": "Eurasian Jackdaw",
            "scientific_name": "Corvus monedula",
            "start_time": 135.0,
            "end_time": 138.0,
            "confidence": 0.6515362858772278
        },
        {
            "common_name": "Eurasian Jackdaw",
            "scientific_name": "Corvus monedula",
            "start_time": 162.0,
            "end_time": 165.0,
            "confidence": 0.6665970683097839
        },
        {
            "common_name": "Eurasian Jackdaw",
            "scientific_name": "Corvus monedula",
            "start_time": 168.0,
            "end_time": 171.0,
            "confidence": 0.5058353543281555
        },
        {
            "common_name": "Eurasian Jackdaw",
            "scientific_name": "Corvus monedula",
            "start_time": 240.0,
            "end_time": 243.0,
            "confidence": 0.5866958498954773
        },
        {
            "common_name": "Eurasian Green Woodpecker",
            "scientific_name": "Picus viridis",
            "start_time": 261.0,
            "end_time": 264.0,
            "confidence": 0.95094895362854
        },
        {
            "common_name": "Eurasian Jackdaw",
            "scientific_name": "Corvus monedula",
            "start_time": 315.0,
            "end_time": 318.0,
            "confidence": 0.7547496557235718
        },
        {
            "common_name": "Eurasian Jackdaw",
            "scientific_name": "Corvus monedula",
            "start_time": 318.0,
            "end_time": 321.0,
            "confidence": 0.591124951839447
        },
        {
            "common_name": "Eurasian Jackdaw",
            "scientific_name": "Corvus monedula",
            "start_time": 342.0,
            "end_time": 345.0,
            "confidence": 0.7187749147415161
        },
        {
            "common_name": "Eurasian Jackdaw",
            "scientific_name": "Corvus monedula",
            "start_time": 366.0,
            "end_time": 369.0,
            "confidence": 0.43235906958580017
        },
        {
            "common_name": "Eurasian Jackdaw",
            "scientific_name": "Corvus monedula",
            "start_time": 372.0,
            "end_time": 375.0,
            "confidence": 0.6588426828384399
        },
        {
            "common_name": "Ring-necked Pheasant",
            "scientific_name": "Phasianus colchicus",
            "start_time": 411.0,
            "end_time": 414.0,
            "confidence": 0.831775426864624
        },
        {
            "common_name": "Eurasian Jackdaw",
            "scientific_name": "Corvus monedula",
            "start_time": 453.0,
            "end_time": 456.0,
            "confidence": 0.4570774435997009
        },
        {
            "common_name": "Eurasian Green Woodpecker",
            "scientific_name": "Picus viridis",
            "start_time": 567.0,
            "end_time": 570.0,
            "confidence": 0.5357754230499268
        },
        {
            "common_name": "Eurasian Green Woodpecker",
            "scientific_name": "Picus viridis",
            "start_time": 570.0,
            "end_time": 573.0,
            "confidence": 0.7788087129592896
        },
        {
            "common_name": "Eurasian Jackdaw",
            "scientific_name": "Corvus monedula",
            "start_time": 591.0,
            "end_time": 594.0,
            "confidence": 0.5694308280944824
        },
        {
            "common_name": "Eurasian Jackdaw",
            "scientific_name": "Corvus monedula",
            "start_time": 621.0,
            "end_time": 624.0,
            "confidence": 0.4494706690311432
        },
        {
            "common_name": "Ring-necked Pheasant",
            "scientific_name": "Phasianus colchicus",
            "start_time": 642.0,
            "end_time": 645.0,
            "confidence": 0.5896347761154175
        },
        {
            "common_name": "Eurasian Jackdaw",
            "scientific_name": "Corvus monedula",
            "start_time": 756.0,
            "end_time": 759.0,
            "confidence": 0.45605310797691345
        },
        {
            "common_name": "Eurasian Jackdaw",
            "scientific_name": "Corvus monedula",
            "start_time": 951.0,
            "end_time": 954.0,
            "confidence": 0.7189891338348389
        },
        {
            "common_name": "Eurasian Blue Tit",
            "scientific_name": "Cyanistes caeruleus",
            "start_time": 1092.0,
            "end_time": 1095.0,
            "confidence": 0.7729915380477905
        },
        {
            "common_name": "Eurasian Green Woodpecker",
            "scientific_name": "Picus viridis",
            "start_time": 1098.0,
            "end_time": 1101.0,
            "confidence": 0.49628183245658875
        },
        {
            "common_name": "Eurasian Green Woodpecker",
            "scientific_name": "Picus viridis",
            "start_time": 1101.0,
            "end_time": 1104.0,
            "confidence": 0.7474011778831482
        },
        {
            "common_name": "Eurasian Jackdaw",
            "scientific_name": "Corvus monedula",
            "start_time": 1113.0,
            "end_time": 1116.0,
            "confidence": 0.6183817386627197
        },
        {
            "common_name": "Eurasian Jackdaw",
            "scientific_name": "Corvus monedula",
            "start_time": 1119.0,
            "end_time": 1122.0,
            "confidence": 0.5972266793251038
        },
        {
            "common_name": "Eurasian Jackdaw",
            "scientific_name": "Corvus monedula",
            "start_time": 1125.0,
            "end_time": 1128.0,
            "confidence": 0.6878095269203186
        }
    ],
    "original_chan1.mp3": [
        {
            "common_name": "Eurasian Jackdaw",
            "scientific_name": "Corvus monedula",
            "start_time": 162.0,
            "end_time": 165.0,
            "confidence": 0.43059423565864563
        },
        {
            "common_name": "Eurasian Jackdaw",
            "scientific_name": "Corvus monedula",
            "start_time": 165.0,
            "end_time": 168.0,
            "confidence": 0.6772862672805786
        },
        {
            "common_name": "Eurasian Jackdaw",
            "scientific_name": "Corvus monedula",
            "start_time": 168.0,
            "end_time": 171.0,
            "confidence": 0.7296843528747559
        },
        {
            "common_name": "Eurasian Green Woodpecker",
            "scientific_name": "Picus viridis",
            "start_time": 261.0,
            "end_time": 264.0,
            "confidence": 0.8998121023178101
        },
        {
            "common_name": "Eurasian Jackdaw",
            "scientific_name": "Corvus monedula",
            "start_time": 279.0,
            "end_time": 282.0,
            "confidence": 0.5788547396659851
        },
        {
            "common_name": "Eurasian Jackdaw",
            "scientific_name": "Corvus monedula",
            "start_time": 282.0,
            "end_time": 285.0,
            "confidence": 0.4842442572116852
        },
        {
            "common_name": "Eurasian Jackdaw",
            "scientific_name": "Corvus monedula",
            "start_time": 315.0,
            "end_time": 318.0,
            "confidence": 0.5853859782218933
        },
        {
            "common_name": "Eurasian Jackdaw",
            "scientific_name": "Corvus monedula",
            "start_time": 318.0,
            "end_time": 321.0,
            "confidence": 0.6190344095230103
        },
        {
            "common_name": "Eurasian Jackdaw",
            "scientific_name": "Corvus monedula",
            "start_time": 342.0,
            "end_time": 345.0,
            "confidence": 0.620076596736908
        },
        {
            "common_name": "Eurasian Jackdaw",
            "scientific_name": "Corvus monedula",
            "start_time": 369.0,
            "end_time": 372.0,
            "confidence": 0.6410224437713623
        },
        {
            "common_name": "Eurasian Jackdaw",
            "scientific_name": "Corvus monedula",
            "start_time": 372.0,
            "end_time": 375.0,
            "confidence": 0.7180480360984802
        },
        {
            "common_name": "Ring-necked Pheasant",
            "scientific_name": "Phasianus colchicus",
            "start_time": 411.0,
            "end_time": 414.0,
            "confidence": 0.7735528349876404
        },
        {
            "common_name": "Eurasian Jackdaw",
            "scientific_name": "Corvus monedula",
            "start_time": 441.0,
            "end_time": 444.0,
            "confidence": 0.6391838788986206
        },
        {
            "common_name": "Eurasian Green Woodpecker",
            "scientific_name": "Picus viridis",
            "start_time": 570.0,
            "end_time": 573.0,
            "confidence": 0.5178363919258118
        },
        {
            "common_name": "Eurasian Jackdaw",
            "scientific_name": "Corvus monedula",
            "start_time": 591.0,
            "end_time": 594.0,
            "confidence": 0.4505828320980072
        },
        {
            "common_name": "Eurasian Jackdaw",
            "scientific_name": "Corvus monedula",
            "start_time": 621.0,
            "end_time": 624.0,
            "confidence": 0.49023309350013733
        },
        {
            "common_name": "Ring-necked Pheasant",
            "scientific_name": "Phasianus colchicus",
            "start_time": 642.0,
            "end_time": 645.0,
            "confidence": 0.5892147421836853
        },
        {
            "common_name": "Eurasian Jackdaw",
            "scientific_name": "Corvus monedula",
            "start_time": 951.0,
            "end_time": 954.0,
            "confidence": 0.567337691783905
        },
        {
            "common_name": "Eurasian Green Woodpecker",
            "scientific_name": "Picus viridis",
            "start_time": 1101.0,
            "end_time": 1104.0,
            "confidence": 0.6154307723045349
        },
        {
            "common_name": "Eurasian Jackdaw",
            "scientific_name": "Corvus monedula",
            "start_time": 1113.0,
            "end_time": 1116.0,
            "confidence": 0.5060279965400696
        },
        {
            "common_name": "Eurasian Jackdaw",
            "scientific_name": "Corvus monedula",
            "start_time": 1119.0,
            "end_time": 1122.0,
            "confidence": 0.5812739729881287
        },
        {
            "common_name": "Eurasian Jackdaw",
            "scientific_name": "Corvus monedula",
            "start_time": 1125.0,
            "end_time": 1128.0,
            "confidence": 0.5182605385780334
        }
    ],
    "pf_chan2.mp3": [
        {
            "common_name": "Common Sandpiper",
            "scientific_name": "Actitis hypoleucos",
            "start_time": 1020.0,
            "end_time": 1023.0,
            "confidence": 0.5182037949562073
        }
    ],
    "pf_chan4.mp3": [
        {
            "common_name": "Ring-necked Pheasant",
            "scientific_name": "Phasianus colchicus",
            "start_time": 411.0,
            "end_time": 414.0,
            "confidence": 0.6932026743888855
        },
        {
            "common_name": "Eurasian Green Woodpecker",
            "scientific_name": "Picus viridis",
            "start_time": 1101.0,
            "end_time": 1104.0,
            "confidence": 0.7794631123542786
        }
    ],
    "sep_chan3.mp3": [
        {
            "common_name": "Eurasian Jackdaw",
            "scientific_name": "Corvus monedula",
            "start_time": 135.0,
            "end_time": 138.0,
            "confidence": 0.7300891280174255
        },
        {
            "common_name": "Eurasian Jackdaw",
            "scientific_name": "Corvus monedula",
            "start_time": 162.0,
            "end_time": 165.0,
            "confidence": 0.4365418255329132
        },
        {
            "common_name": "Eurasian Magpie",
            "scientific_name": "Pica pica",
            "start_time": 165.0,
            "end_time": 168.0,
            "confidence": 0.414852499961853
        },
        {
            "common_name": "Eurasian Jackdaw",
            "scientific_name": "Corvus monedula",
            "start_time": 168.0,
            "end_time": 171.0,
            "confidence": 0.611676037311554
        },
        {
            "common_name": "Eurasian Jackdaw",
            "scientific_name": "Corvus monedula",
            "start_time": 240.0,
            "end_time": 243.0,
            "confidence": 0.7486761212348938
        },
        {
            "common_name": "Eurasian Green Woodpecker",
            "scientific_name": "Picus viridis",
            "start_time": 261.0,
            "end_time": 264.0,
            "confidence": 0.9319406151771545
        },
        {
            "common_name": "Eurasian Jackdaw",
            "scientific_name": "Corvus monedula",
            "start_time": 372.0,
            "end_time": 375.0,
            "confidence": 0.5568544864654541
        },
        {
            "common_name": "Ring-necked Pheasant",
            "scientific_name": "Phasianus colchicus",
            "start_time": 411.0,
            "end_time": 414.0,
            "confidence": 0.40875884890556335
        },
        {
            "common_name": "Eurasian Jackdaw",
            "scientific_name": "Corvus monedula",
            "start_time": 441.0,
            "end_time": 444.0,
            "confidence": 0.5380921959877014
        },
        {
            "common_name": "Eurasian Jackdaw",
            "scientific_name": "Corvus monedula",
            "start_time": 486.0,
            "end_time": 489.0,
            "confidence": 0.4844024181365967
        },
        {
            "common_name": "Eurasian Green Woodpecker",
            "scientific_name": "Picus viridis",
            "start_time": 570.0,
            "end_time": 573.0,
            "confidence": 0.5278061628341675
        },
        {
            "common_name": "Eurasian Jackdaw",
            "scientific_name": "Corvus monedula",
            "start_time": 591.0,
            "end_time": 594.0,
            "confidence": 0.5751543641090393
        },
        {
            "common_name": "Eurasian Jackdaw",
            "scientific_name": "Corvus monedula",
            "start_time": 621.0,
            "end_time": 624.0,
            "confidence": 0.5163215398788452
        },
        {
            "common_name": "Eurasian Jackdaw",
            "scientific_name": "Corvus monedula",
            "start_time": 756.0,
            "end_time": 759.0,
            "confidence": 0.502186119556427
        },
        {
            "common_name": "Eurasian Jackdaw",
            "scientific_name": "Corvus monedula",
            "start_time": 951.0,
            "end_time": 954.0,
            "confidence": 0.6837499141693115
        },
        {
            "common_name": "Eurasian Jackdaw",
            "scientific_name": "Corvus monedula",
            "start_time": 1113.0,
            "end_time": 1116.0,
            "confidence": 0.5650463700294495
        },
        {
            "common_name": "Eurasian Jackdaw",
            "scientific_name": "Corvus monedula",
            "start_time": 1125.0,
            "end_time": 1128.0,
            "confidence": 0.7835625410079956
        }
    ],
    "sep_chan4.mp3": [
        {
            "common_name": "Ring-necked Pheasant",
            "scientific_name": "Phasianus colchicus",
            "start_time": 99.0,
            "end_time": 102.0,
            "confidence": 0.72464919090271
        },
        {
            "common_name": "Eurasian Jackdaw",
            "scientific_name": "Corvus monedula",
            "start_time": 135.0,
            "end_time": 138.0,
            "confidence": 0.6013109683990479
        },
        {
            "common_name": "Eurasian Jackdaw",
            "scientific_name": "Corvus monedula",
            "start_time": 168.0,
            "end_time": 171.0,
            "confidence": 0.6381814479827881
        },
        {
            "common_name": "Eurasian Jackdaw",
            "scientific_name": "Corvus monedula",
            "start_time": 240.0,
            "end_time": 243.0,
            "confidence": 0.49153459072113037
        },
        {
            "common_name": "Eurasian Green Woodpecker",
            "scientific_name": "Picus viridis",
            "start_time": 261.0,
            "end_time": 264.0,
            "confidence": 0.9533976912498474
        },
        {
            "common_name": "Ring-necked Pheasant",
            "scientific_name": "Phasianus colchicus",
            "start_time": 288.0,
            "end_time": 291.0,
            "confidence": 0.7706454992294312
        },
        {
            "common_name": "Eurasian Jackdaw",
            "scientific_name": "Corvus monedula",
            "start_time": 315.0,
            "end_time": 318.0,
            "confidence": 0.5559753775596619
        },
        {
            "common_name": "Eurasian Jackdaw",
            "scientific_name": "Corvus monedula",
            "start_time": 318.0,
            "end_time": 321.0,
            "confidence": 0.7399863004684448
        },
        {
            "common_name": "Eurasian Jackdaw",
            "scientific_name": "Corvus monedula",
            "start_time": 366.0,
            "end_time": 369.0,
            "confidence": 0.5599998831748962
        },
        {
            "common_name": "Eurasian Jackdaw",
            "scientific_name": "Corvus monedula",
            "start_time": 369.0,
            "end_time": 372.0,
            "confidence": 0.6663203239440918
        },
        {
            "common_name": "Eurasian Jackdaw",
            "scientific_name": "Corvus monedula",
            "start_time": 372.0,
            "end_time": 375.0,
            "confidence": 0.5590009093284607
        },
        {
            "common_name": "Ring-necked Pheasant",
            "scientific_name": "Phasianus colchicus",
            "start_time": 411.0,
            "end_time": 414.0,
            "confidence": 0.8823947906494141
        },
        {
            "common_name": "Eurasian Jackdaw",
            "scientific_name": "Corvus monedula",
            "start_time": 453.0,
            "end_time": 456.0,
            "confidence": 0.47183355689048767
        },
        {
            "common_name": "Eurasian Green Woodpecker",
            "scientific_name": "Picus viridis",
            "start_time": 567.0,
            "end_time": 570.0,
            "confidence": 0.6821316480636597
        },
        {
            "common_name": "Eurasian Green Woodpecker",
            "scientific_name": "Picus viridis",
            "start_time": 570.0,
            "end_time": 573.0,
            "confidence": 0.8103072643280029
        },
        {
            "common_name": "Ring-necked Pheasant",
            "scientific_name": "Phasianus colchicus",
            "start_time": 642.0,
            "end_time": 645.0,
            "confidence": 0.7793080806732178
        },
        {
            "common_name": "Eurasian Nuthatch",
            "scientific_name": "Sitta europaea",
            "start_time": 696.0,
            "end_time": 699.0,
            "confidence": 0.49456629157066345
        },
        {
            "common_name": "Eurasian Nuthatch",
            "scientific_name": "Sitta europaea",
            "start_time": 723.0,
            "end_time": 726.0,
            "confidence": 0.5732343196868896
        },
        {
            "common_name": "Eurasian Nuthatch",
            "scientific_name": "Sitta europaea",
            "start_time": 807.0,
            "end_time": 810.0,
            "confidence": 0.5822065472602844
        },
        {
            "common_name": "Eurasian Jackdaw",
            "scientific_name": "Corvus monedula",
            "start_time": 951.0,
            "end_time": 954.0,
            "confidence": 0.5333055853843689
        },
        {
            "common_name": "Eurasian Green Woodpecker",
            "scientific_name": "Picus viridis",
            "start_time": 1098.0,
            "end_time": 1101.0,
            "confidence": 0.4999580383300781
        },
        {
            "common_name": "Eurasian Green Woodpecker",
            "scientific_name": "Picus viridis",
            "start_time": 1101.0,
            "end_time": 1104.0,
            "confidence": 0.9607899188995361
        },
        {
            "common_name": "Eurasian Jackdaw",
            "scientific_name": "Corvus monedula",
            "start_time": 1125.0,
            "end_time": 1128.0,
            "confidence": 0.5650131106376648
        }
    ],
    "pf_chan1.mp3": []
}